AUTHORS.rst
CONTRIBUTING.rst
HISTORY.rst
LICENSE
MANIFEST.in
README.rst
setup.cfg
setup.py
djangogirls_organization/__init__.py
djangogirls_organization/cli.py
djangogirls_organization/djangogirls_organization.py
djangogirls_organization.egg-info/PKG-INFO
djangogirls_organization.egg-info/SOURCES.txt
djangogirls_organization.egg-info/dependency_links.txt
djangogirls_organization.egg-info/entry_points.txt
djangogirls_organization.egg-info/not-zip-safe
djangogirls_organization.egg-info/requires.txt
djangogirls_organization.egg-info/top_level.txt
docs/Makefile
docs/authors.rst
docs/conf.py
docs/contributing.rst
docs/djangogirls_organization.rst
docs/history.rst
docs/index.rst
docs/installation.rst
docs/make.bat
docs/modules.rst
docs/readme.rst
docs/usage.rst
docs/_build/html/_static/ajax-loader.gif
docs/_build/html/_static/comment-bright.png
docs/_build/html/_static/comment-close.png
docs/_build/html/_static/comment.png
docs/_build/html/_static/down-pressed.png
docs/_build/html/_static/down.png
docs/_build/html/_static/file.png
docs/_build/html/_static/minus.png
docs/_build/html/_static/plus.png
docs/_build/html/_static/up-pressed.png
docs/_build/html/_static/up.png
tests/test_djangogirls_organization.py