Metadata-Version: 1.1
Name: djangogirls-organization
Version: 0.1.0
Summary: Prints necessary things to do Django Girls Workshop
Home-page: https://github.com/carogomezt/djangogirls_organization
Author: Carolina Gomez Trejos
Author-email: carolina9511@gmail.com
License: MIT license
Keywords: djangogirls_organization
Platform: UNKNOWN
Classifier: Development Status :: 2 - Pre-Alpha
Classifier: Intended Audience :: Developers
Classifier: License :: OSI Approved :: MIT License
Classifier: Natural Language :: English
Classifier: Programming Language :: Python :: 2
Classifier: Programming Language :: Python :: 2.7
Classifier: Programming Language :: Python :: 3
Classifier: Programming Language :: Python :: 3.4
Classifier: Programming Language :: Python :: 3.5
Classifier: Programming Language :: Python :: 3.6
